rpc_bitcoin/__init__.py
rpc_bitcoin/rpc_bitcoin.py
rpc_bitcoin-0.0.1.dist-info/LICENSE
rpc_bitcoin-0.0.1.dist-info/METADATA
rpc_bitcoin-0.0.1.dist-info/WHEEL
rpc_bitcoin-0.0.1.dist-info/top_level.txt
rpc_bitcoin-0.0.1.dist-info/RECORD
