Metadata-Version: 2.1
Name: rpc-bitcoin
Version: 0.0.1
Summary: RPC client for connect to bitcoind
Author-email: pythcoiner <pythcoiner@proton.me>
License: BSD 3-Clause License
Project-URL: Homepage, https://github.com/pythcoiner/BitcoinRpcClient
Keywords: bitcoin,rpc
Classifier: Topic :: Office/Business :: Financial
Classifier: Topic :: Security :: Cryptography
Classifier: Topic :: Software Development :: Libraries :: Python Modules
Requires-Python: >=3.9
License-File: LICENSE
